aimap/__init__.py
aimap/aimap_config.py
aimap/aimap_tools.py
aimap-1.5.0.data/scripts/Adenosine_to_inosine.py
aimap-1.5.0.dist-info/LICENSE
aimap-1.5.0.dist-info/METADATA
aimap-1.5.0.dist-info/WHEEL
aimap-1.5.0.dist-info/top_level.txt
aimap-1.5.0.dist-info/RECORD
