Metadata-Version: 2.1
Name: aimap
Version: 1.5.0
Summary: aimap provides a package and script for finding the modification from Adenosine to inosine (A to I).
Home-page: https://github.com/castualwang/aimap
Download-URL: https://github.com/castualwang/aimap/releases
Author: Sai Wang
Author-email: skyws@outlook.com
License: MIT
Keywords: sequence analysis
Platform: Posix; MacOS X
Classifier: Development Status :: 4 - Beta
Classifier: Environment :: Console
Classifier: Intended Audience :: Science/Research
Classifier: License :: OSI Approved :: MIT License
Classifier: Natural Language :: English
Classifier: Operating System :: MacOS :: MacOS X
Classifier: Operating System :: POSIX :: Linux
Classifier: Programming Language :: Python
Classifier: Programming Language :: Python :: 3
Classifier: Programming Language :: Python :: 3.5
Classifier: Programming Language :: Python :: 3.6
Classifier: Topic :: Scientific/Engineering :: Bio-Informatics
Requires-Python: >=3
License-File: LICENSE
Requires-Dist: biopython
Requires-Dist: pandas
